{
    "version": "3.16.7",
    "flags": {},
    "shapes": [
        {
            "label": "KZXB",
            "line_color": null,
            "fill_color": null,
            "points": [
                [
                    2425.9259259259256,
                    225.92592592592592
                ],
                [
                    3999.0,
                    841.0
                ]
            ],
            "shape_type": "rectangle",
            "flags": {}
        }
    ],
    "lineColor": [
        0,
        255,
        0,
        128
    ],
    "fillColor": [
        255,
        0,
        0,
        128
    ],
    "imagePath": "0927 (906).JPG",
    "imageData": null,
    "imageHeight": 3000,
    "imageWidth": 4000
}